Workbook

Sheet Sheet1
A1: Net Income Per Month | B1: Amount | D1: Monthly cost | E1: Amount | G1: Monthly | H1: Amount | J1: Stocks | K1: Price
A2: Conner JSE | B2: =23*40*0.817*4 -> 3006.56 | D2: Groceries | E2: 600 | G2: Spotify Conner | H2: 3.5 | J2: Kensey IRA | K2: 50
A3: Kensey Nanny Aaron | B3: =24*9.5*4 -> 912 | D3: Gas | E3: 180 | G3: Spotify Kensey | H3: 3.5 | J3: Conner IRA | K3: 100
A4: Kensey Nanny Griffin | B4: =25*8*4 -> 800 | D4: chipolte | E4: 160 | G4: Mint Mobile Kensey | H4: 20 | J4: Conner Mutual Funds | K4: 100
A5: Kensey PST | B5: =24.5*20*4 -> 1960 | D5: Subscriptions | E5: =SUM(H2:H16) -> 957.12333 | G5: Mint Mobile Conner | H5: 20
A6: Net income Per Month | B6: =SUM(B2:B5) -> 6678.56 | D6: Stocks | E6: =SUM(K2:K4) -> 250 | G6: Apple Conner | H6: 1
D7: Tithe | E7: 700 | G7: ASPCA Conner | H7: 10
D8: Shopping | E8: 250 | G8: Insurance | H8: =K14 -> 350 | J8: Insurance | K8: Monthly | L8: Yearly
D9: rent | E9: 1735 | G9: Wifi | H9: 50.29 | J9: Rav 4 | K9: 350 | L9: 879.6
A10: Total | B10: Amount | D10: School | E10: =SUM(H19:H20) -> 300 | G10: Gym | H10: 120 | J10: Corolla | K10: 0 | L10: 971.21
A11: Profit | B11: =B6 -> 6678.56 | D11: Total | E11: =SUM(E2:E10) -> 5132.1233 | G11: Costco Memberhsip | H11: =130/12 -> 10.833333 | J11: Ninja 400 | K11: 0 | L11: 321.34
A12: Cost | B12: =E11 -> 5132.1233 | G12: Netflix | H12: 8 | J12: Triumph | K12: 0 | L12: 107.53
A13: Left | B13: =B11-B12 -> 1546.4367 | D13: ENVELOPE DIS SHIT | G13: Train | H13: 88 | J13: Renters | K13: 0 | L13: 96
A14: =ROUND(B13,-2)-200 -> 1300 | D14: Savings per month for annual payment | G14: Oura rings | H14: 12 | J14: Total | K14: =SUM(K9:K13) -> 350
A15: =12*A14 -> 15600 | B15: i*=8% | D15: Kensey Classes | E15: =H19 -> 300 | G15: Wifi | H15: 60
A16: 16800 saved per year | B16: year | D16: Mint Mobile Kensey | E16: =H4 -> 20 | G16: Utilities | H16: 200
A17: =A15 -> 15600 | B17: 1 | D17: Mint Mobile Conner | E17: 20
A18: =FV(0.08,1,,A17)*-1 -> 16848 | B18: 2 | D18: Costco Membership | E18: =H11 -> 10.833333 | G18: School | H18: Cost
A19: =FV(0.08,1,,A18)*-1 -> 18195.84 | B19: 3 | D19: total | E19: =SUM(E15:E18) -> 350.83333 | G19: Kensey Classes | H19: =600/2 -> 300
A20: =FV(0.08,1,,A19)*-1 -> 19651.507 | B20: 4 | G20: Kensey Debt | H20: 0
A21: =FV(0.08,1,,A20)*-1 -> 21223.628 | B21: 5 | D21: total saved over 5 years with 8% market returns
A22: =FV(0.08,1,,A21)*-1 -> 22921.518 | B22: 6 | D22: =SUM(A17:A21) -> 91518.975
A23: =FV(0.08,1,,A22)*-1 -> 24755.239 | B23: 7
A24: =FV(0.08,1,,A23)*-1 -> 26735.659 | B24: 8
A25: =FV(0.08,1,,A24)*-1 -> 28874.511 | B25: 9 | D25: total saved over 10 years with 8% market returns
A26: =FV(0.08,1,,A25)*-1 -> 31184.472 | B26: =B25+1 -> 10 | D26: =SUM(A17:A26) -> 225990.37
A27: =FV(0.08,1,,A26)*-1 -> 33679.23 | B27: =B26+1 -> 11
A28: =FV(0.08,1,,A27)*-1 -> 36373.568 | B28: =B27+1 -> 12
A29: =FV(0.08,1,,A28)*-1 -> 39283.454 | B29: =B28+1 -> 13
A30: =FV(0.08,1,,A29)*-1 -> 42426.13 | B30: =B29+1 -> 14 | D30: total saved over 15 years with 8% market returns
A31: =FV(0.08,1,,A30)*-1 -> 45820.221 | B31: =B30+1 -> 15 | D31: =SUM(A17:A31) -> 423572.98
A32: =FV(0.08,1,,A31)*-1 -> 49485.838 | B32: =B31+1 -> 16
A33: =FV(0.08,1,,A32)*-1 -> 53444.705 | B33: =B32+1 -> 17
A34: =FV(0.08,1,,A33)*-1 -> 57720.282 | B34: =B33+1 -> 18
A35: =FV(0.08,1,,A34)*-1 -> 62337.904 | B35: =B34+1 -> 19 | D35: total saved over 20 years with 8% market returns
A36: =FV(0.08,1,,A35)*-1 -> 67324.937 | B36: =B35+1 -> 20 | D36: =SUM(A17:A36) -> 713886.64

Sheet Sheet2
A1: =Sheet1!D1 -> Monthly cost | B1: =Sheet1!E1 -> Amount | D1: =Sheet1!D13 -> ENVELOPE DIS SHIT | E1: amount | G1: =Sheet1!A10 -> Total | H1: =Sheet1!B10 -> Amount | J1: Subscriptions | K1: =Sheet1!H1 -> Amount | M1: =Sheet1!J8 -> Insurance | N1: =Sheet1!K8 -> Monthly | P1: =Sheet1!J1 -> Stocks | Q1: =Sheet1!K1 -> Price | S1: =Sheet1!G18 -> School | T1: =Sheet1!H18 -> Cost
A2: =Sheet1!D2 -> Groceries | B2: =Sheet1!E2 -> 600 | D2: =Sheet1!D14 -> Savings per month for annual payment | E2: =Sheet1!E14 -> 0 | G2: =Sheet1!A11 -> Profit | H2: =Sheet1!B11 -> 6678.56 | J2: =Sheet1!G2 -> Spotify Conner | K2: =Sheet1!H2 -> 3.5 | M2: =Sheet1!J9 -> Rav 4 | N2: =Sheet1!K9 -> 350 | P2: =Sheet1!J2 -> Kensey IRA | Q2: =Sheet1!K2 -> 50 | S2: =Sheet1!G19 -> Kensey Classes | T2: =Sheet1!H19 -> 300
A3: =Sheet1!D3 -> Gas | B3: =Sheet1!E3 -> 180 | D3: =Sheet1!D15 -> Kensey Classes | E3: =Sheet1!E15 -> 300 | G3: =Sheet1!A12 -> Cost | H3: =Sheet1!B12 -> 5132.1233 | J3: =Sheet1!G3 -> Spotify Kensey | K3: =Sheet1!H3 -> 3.5 | M3: =Sheet1!J10 -> Corolla | N3: =Sheet1!K10 -> 0 | P3: =Sheet1!J3 -> Conner IRA | Q3: =Sheet1!K3 -> 100 | S3: =Sheet1!G20 -> Kensey Debt | T3: =Sheet1!H20 -> 0
A4: =Sheet1!D4 -> chipolte | B4: =Sheet1!E4 -> 160 | D4: =Sheet1!D16 -> Mint Mobile Kensey | E4: =Sheet1!E16 -> 20 | G4: =Sheet1!A13 -> Left | H4: =Sheet1!B13 -> 1546.4367 | J4: =Sheet1!G4 -> Mint Mobile Kensey | K4: =Sheet1!H4 -> 20 | M4: =Sheet1!J11 -> Ninja 400 | N4: =Sheet1!K11 -> 0 | P4: =Sheet1!J4 -> Conner Mutual Funds | Q4: =Sheet1!K4 -> 100
A5: =Sheet1!D5 -> Subscriptions | B5: =Sheet1!E5 -> 957.12333 | D5: =Sheet1!D17 -> Mint Mobile Conner | E5: =Sheet1!E17 -> 20 | J5: =Sheet1!G5 -> Mint Mobile Conner | K5: =Sheet1!H5 -> 20 | M5: =Sheet1!J12 -> Triumph | N5: =Sheet1!K12 -> 0
A6: =Sheet1!D6 -> Stocks | B6: =Sheet1!E6 -> 250 | D6: =Sheet1!D18 -> Costco Membership | E6: =Sheet1!E18 -> 10.833333 | J6: =Sheet1!G6 -> Apple Conner | K6: =Sheet1!H6 -> 1 | M6: =Sheet1!J13 -> Renters | N6: =Sheet1!K13 -> 0
A7: =Sheet1!D7 -> Tithe | B7: =Sheet1!E7 -> 700 | D7: =Sheet1!D19 -> total | E7: =Sheet1!E19 -> 350.83333 | J7: =Sheet1!G7 -> ASPCA Conner | K7: =Sheet1!H7 -> 10 | M7: =Sheet1!J14 -> Total | N7: =Sheet1!K14 -> 350
A8: =Sheet1!D8 -> Shopping | B8: =Sheet1!E8 -> 250 | J8: =Sheet1!G8 -> Insurance | K8: =Sheet1!H8 -> 350
A9: =Sheet1!D9 -> rent | B9: =Sheet1!E9 -> 1735 | J9: =Sheet1!G9 -> Wifi | K9: =Sheet1!H9 -> 50.29
A10: =Sheet1!D10 -> School | B10: =Sheet1!E10 -> 300 | J10: =Sheet1!G10 -> Gym | K10: =Sheet1!H10 -> 120
A11: =Sheet1!D11 -> Total | B11: =Sheet1!E11 -> 5132.1233 | J11: =Sheet1!G11 -> Costco Memberhsip | K11: =Sheet1!H11 -> 10.833333
J12: =Sheet1!G12 -> Netflix | K12: =Sheet1!H12 -> 8
J13: =Sheet1!G13 -> Train | K13: =Sheet1!H13 -> 88
J14: =Sheet1!G14 -> Oura rings | K14: =Sheet1!H14 -> 12
J15: =Sheet1!G15 -> Wifi | K15: =Sheet1!H15 -> 60
J16: =Sheet1!G16 -> Utilities | K16: =Sheet1!H16 -> 200
J17: total | K17: =SUM(K2:K16) -> 957.12333
